django_nh3/__init__.py
django_nh3/apps.py
django_nh3/forms.py
django_nh3/models.py
django_nh3/py.typed
django_nh3/utils.py
django_nh3/templatetags/__init__.py
django_nh3/templatetags/nh3_tags.py
django_nh3-0.2.1.dist-info/licenses/LICENSE
django_nh3-0.2.1.dist-info/METADATA
django_nh3-0.2.1.dist-info/WHEEL
django_nh3-0.2.1.dist-info/top_level.txt
django_nh3-0.2.1.dist-info/RECORD
