Metadata-Version: 2.4
Name: django-nh3
Version: 0.2.1
Summary: Django integration with for nh3, Python binding to Ammonia HTML sanitizer Rust crate.
Author-email: Mark Walker <theshow@gmail.com>
License: MIT License
Project-URL: Changelog, https://github.com/marksweb/django-nh3/blob/main/CHANGELOG.rst
Project-URL: Mastodon, https://fosstodon.org/@markwalker
Project-URL: Repository, https://github.com/marksweb/django-nh3
Project-URL: Twitter, https://twitter.com/markwalker_
Keywords: Django
Classifier: Development Status :: 4 - Beta
Classifier: Framework :: Django :: 3.2
Classifier: Framework :: Django :: 4.0
Classifier: Framework :: Django :: 4.1
Classifier: Framework :: Django :: 4.2
Classifier: Framework :: Django :: 5.0
Classifier: Framework :: Django :: 5.1
Classifier: Intended Audience :: Developers
Classifier: License :: OSI Approved :: MIT License
Classifier: Natural Language :: English
Classifier: Operating System :: OS Independent
Classifier: Programming Language :: Python :: 3 :: Only
Classifier: Programming Language :: Python :: 3.10
Classifier: Programming Language :: Python :: 3.11
Classifier: Programming Language :: Python :: 3.12
Classifier: Programming Language :: Python :: 3.13
Classifier: Programming Language :: Python :: 3.14
Classifier: Programming Language :: Python :: Implementation :: CPython
Classifier: Typing :: Typed
Requires-Python: >=3.10
License-File: LICENSE
Requires-Dist: django>=3.2
Requires-Dist: nh3
Requires-Dist: typing-extensions
Dynamic: license-file
